utils/__init__.py
utils/module.py
utils/tools.py
mattli_ds-1.0.0.dist-info/LICENSE
mattli_ds-1.0.0.dist-info/METADATA
mattli_ds-1.0.0.dist-info/WHEEL
mattli_ds-1.0.0.dist-info/top_level.txt
mattli_ds-1.0.0.dist-info/RECORD
