Metadata-Version: 2.1
Name: mattli-ds
Version: 1.0.0
Summary: userful tools for data science projects
Home-page: https://github.com/mattli/deeplearning
Author: Mattli
Author-email: matt.li76@icloud.com
Classifier: License :: OSI Approved :: MIT License
Classifier: Programming Language :: Python :: 3
Classifier: Programming Language :: Python :: 3.5
Classifier: Programming Language :: Python :: 3.6
Classifier: Programming Language :: Python :: 3.7
Classifier: Operating System :: OS Independent
License-File: LICENSE
Requires-Dist: python-box (==6.0.2)
Requires-Dist: ensure (==1.0.2)
Requires-Dist: pyYAML
Requires-Dist: joblib
